macaetr/__init__.py
macaetr/maca.py
macaetr/metadata/__init__.py
macaetr/metadata/livneh_cell_data.csv
macaetr/metadata/macav2_cell_data.csv
macaetr-0.0.3.post1.dist-info/LICENSE
macaetr-0.0.3.post1.dist-info/LICENSE~
macaetr-0.0.3.post1.dist-info/METADATA
macaetr-0.0.3.post1.dist-info/WHEEL
macaetr-0.0.3.post1.dist-info/top_level.txt
macaetr-0.0.3.post1.dist-info/RECORD
