Metadata-Version: 2.1
Name: macaetr
Version: 0.0.3.post1
Summary: Download MACA downscaled data, calculate ASCE ETrz
Home-page: https://github.com/WSWUP/MACA-ETr
Author: John Volk
Author-email: john.volk@dri.edu
License: Apache
Platform: Windows
Platform: Linux
Platform: Mac OS X
Classifier: License :: OSI Approved :: Apache Software License
Classifier: Programming Language :: Python :: 3.7
Classifier: Environment :: Console
Classifier: Development Status :: 4 - Beta
Classifier: Topic :: Scientific/Engineering
Classifier: Intended Audience :: Science/Research
Requires-Dist: netCDF4
Requires-Dist: numpy
Requires-Dist: pandas
Requires-Dist: refet (>=0.3.7)
Requires-Dist: scipy (>=1.1.0)
Requires-Dist: xarray
